[1,["89KgHTmstFH6Vo/qjqgtzC"],["spriteFrame"],[["cc.BitmapFont",["_name","fontSize","_fntConfig"],0]],[[0,0,1,2,4]],[[0,"ziyou-yudengji",24,{"commonHeight":24,"fontSize":24,"atlasName":"ziyou-yudengji.png","fontDefDictionary":{"46":{"xOffset":-7,"yOffset":9,"xAdvance":7,"rect":{"x":190,"y":36,"width":21,"height":19}},"48":{"xOffset":-8,"yOffset":-5,"xAdvance":14,"rect":{"x":37,"y":0,"width":30,"height":33}},"49":{"xOffset":-7,"yOffset":-5,"xAdvance":13,"rect":{"x":130,"y":36,"width":24,"height":33}},"50":{"xOffset":-8,"yOffset":-5,"xAdvance":14,"rect":{"x":66,"y":36,"width":29,"height":33}},"51":{"xOffset":-8,"yOffset":-5,"xAdvance":14,"rect":{"x":70,"y":0,"width":30,"height":33}},"52":{"xOffset":-8,"yOffset":-5,"xAdvance":14,"rect":{"x":103,"y":0,"width":30,"height":33}},"53":{"xOffset":-8,"yOffset":-5,"xAdvance":14,"rect":{"x":136,"y":0,"width":30,"height":33}},"54":{"xOffset":-8,"yOffset":-5,"xAdvance":14,"rect":{"x":169,"y":0,"width":30,"height":33}},"55":{"xOffset":-8,"yOffset":-5,"xAdvance":14,"rect":{"x":202,"y":0,"width":30,"height":33}},"56":{"xOffset":-8,"yOffset":-5,"xAdvance":14,"rect":{"x":0,"y":36,"width":30,"height":33}},"57":{"xOffset":-8,"yOffset":-5,"xAdvance":14,"rect":{"x":33,"y":36,"width":30,"height":33}},"76":{"xOffset":-7,"yOffset":-5,"xAdvance":14,"rect":{"x":98,"y":36,"width":29,"height":33}},"86":{"xOffset":-8,"yOffset":-5,"xAdvance":17,"rect":{"x":0,"y":0,"width":34,"height":33}},"120":{"xOffset":-8,"yOffset":0,"xAdvance":14,"rect":{"x":157,"y":36,"width":30,"height":28}}},"kerningDict":{}}]],0,0,[0],[0],[0]]